testercat/__init__.py
testercat-0.0.2.dist-info/METADATA
testercat-0.0.2.dist-info/WHEEL
testercat-0.0.2.dist-info/top_level.txt
testercat-0.0.2.dist-info/RECORD
