Metadata-Version: 2.1
Name: testercat
Version: 0.0.2
Summary: tester
Home-page: https://catalyst.zoho.com/
License: Apache License 2.0
Classifier: Programming Language :: Python :: 3
Classifier: Programming Language :: Python :: 3.9
Classifier: License :: OSI Approved :: Apache Software License
Classifier: Operating System :: OS Independent
Classifier: Development Status :: 4 - Beta
Classifier: Intended Audience :: Developers
Requires-Python: >= 3.9
Requires-Dist: requests (==2.28.1)
